estore/base/event.py
estore_base-0.0.4.dist-info/LICENSE.txt
estore_base-0.0.4.dist-info/METADATA
estore_base-0.0.4.dist-info/WHEEL
estore_base-0.0.4.dist-info/top_level.txt
estore_base-0.0.4.dist-info/RECORD
